{"challenge":{"announcements":[],"are_results_final":true,"end_ms":1494144000000,"id":"0000000000201d27","is_practice_available":true,"result_status":30,"result_status__str":"FINALIZED","start_ms":1494133200000,"tasks":[{"id":"0000000000201b7b","num_attempted":820,"tests":[{"num_solved":820,"type":1,"type__str":"VISIBLE","value":7},{"num_solved":411,"type":2,"type__str":"HIDDEN","value":16}],"title":"Math Encoder"},{"id":"0000000000201c01","num_attempted":424,"tests":[{"num_solved":190,"type":1,"type__str":"VISIBLE","value":13},{"num_solved":97,"type":2,"type__str":"HIDDEN","value":21}],"title":"Center"},{"id":"0000000000201c9a","num_attempted":507,"tests":[{"num_solved":442,"type":1,"type__str":"VISIBLE","value":11},{"num_solved":59,"type":2,"type__str":"HIDDEN","value":32}],"title":"Christmas Tree"}],"title":"Round B 2017"},"full_scoreboard_size":822,"user_scores":[{"competitor":{"country":["Indonesia"],"displayname":"ayaze","id":"0000000000477368","location_info":[],"neverland_ids":["0000000000477367"],"type":1,"type__str":"DEFAULT_COMPETITOR"},"country":"Indonesia","displayname":"ayaze","rank":1,"score_1":100,"score_2":-2642422670,"task_info":[{"penalty_attempts":0,"penalty_micros":450342900,"score":23,"score_by_test":[],"task_id":"0000000000201b7b","tests_definitely_solved":2,"tests_possibly_solved":0,"total_attempts":2},{"penalty_attempts":0,"penalty_micros":2642422670,"score":34,"score_by_test":[],"task_id":"0000000000201c01","tests_definitely_solved":2,"tests_possibly_solved":0,"total_attempts":2},{"penalty_attempts":0,"penalty_micros":2026833240,"score":43,"score_by_test":[],"task_id":"0000000000201c9a","tests_definitely_solved":2,"tests_possibly_solved":0,"total_attempts":2}]},{"competitor":{"country":["South Korea"],"displayname":"pps789","id":"000000000052b1b4","location_info":[],"neverland_ids":["000000000052b1b3"],"type":1,"type__str":"DEFAULT_COMPETITOR"},"country":"South Korea","displayname":"pps789","rank":2,"score_1":100,"score_2":-3430992800,"task_info":[{"penalty_attempts":0,"penalty_micros":375025260,"score":23,"score_by_test":[],"task_id":"0000000000201b7b","tests_definitely_solved":2,"tests_possibly_solved":0,"total_attempts":2},{"penalty_attempts":0,"penalty_micros":1340848200,"score":34,"score_by_test":[],"task_id":"0000000000201c01","tests_definitely_solved":2,"tests_possibly_solved":0,"total_attempts":2},{"penalty_attempts":0,"penalty_micros":3430992800,"score":43,"score_by_test":[],"task_id":"0000000000201c9a","tests_definitely_solved":2,"tests_possibly_solved":0,"total_attempts":2}]},{"competitor":{"country":["China"],"displayname":"saffahyjp","id":"000000000047f8ae","location_info":[],"neverland_ids":["000000000047f8ad"],"type":1,"type__str":"DEFAULT_COMPETITOR"},"country":"China","displayname":"saffahyjp","rank":3,"score_1":100,"score_2":-3438279990,"task_info":[{"penalty_attempts":0,"penalty_micros":938291120,"score":23,"score_by_test":[],"task_id":"0000000000201b7b","tests_definitely_solved":2,"tests_possibly_solved":0,"total_attempts":2},{"penalty_attempts":0,"penalty_micros":1564380120,"score":34,"score_by_test":[],"task_id":"0000000000201c01","tests_definitely_solved":2,"tests_possibly_solved":0,"total_attempts":2},{"penalty_attempts":2,"penalty_micros":2958279990,"score":43,"score_by_test":[],"task_id":"0000000000201c9a","tests_definitely_solved":2,"tests_possibly_solved":0,"total_attempts":4}]},{"competitor":{"country":["Indonesia"],"displayname":"wifi","id":"0000000000488acc","location_info":[],"neverland_ids":["0000000000488acb"],"type":1,"type__str":"DEFAULT_COMPETITOR"},"country":"Indonesia","displayname":"wifi","rank":4,"score_1":100,"score_2":-4033658780,"task_info":[{"penalty_attempts":0,"penalty_micros":385847590,"score":23,"score_by_test":[],"task_id":"0000000000201b7b","tests_definitely_solved":2,"tests_possibly_solved":0,"total_attempts":2},{"penalty_attempts":0,"penalty_micros":1826227860,"score":34,"score_by_test":[],"task_id":"0000000000201c01","tests_definitely_solved":2,"tests_possibly_solved":0,"total_attempts":2},{"penalty_attempts":0,"penalty_micros":4033658780,"score":43,"score_by_test":[],"task_id":"0000000000201c9a","tests_definitely_solved":2,"tests_possibly_solved":0,"total_attempts":2}]},{"competitor":{"country":["India"],"displayname":"uhateme","id":"000000000056fe20","location_info":[],"neverland_ids":["000000000056fe1f"],"type":1,"type__str":"DEFAULT_COMPETITOR"},"country":"India","displayname":"uhateme","rank":5,"score_1":100,"score_2":-4555843110,"task_info":[{"penalty_attempts":0,"penalty_micros":460360580,"score":23,"score_by_test":[],"task_id":"0000000000201b7b","tests_definitely_solved":2,"tests_possibly_solved":0,"total_attempts":2},{"penalty_attempts":0,"penalty_micros":2506206410,"score":34,"score_by_test":[],"task_id":"0000000000201c01","tests_definitely_solved":2,"tests_possibly_solved":0,"total_attempts":2},{"penalty_attempts":0,"penalty_micros":4555843110,"score":43,"score_by_test":[],"task_id":"0000000000201c9a","tests_definitely_solved":2,"tests_possibly_solved":0,"total_attempts":2}]},{"competitor":{"country":["Vietnam"],"displayname":"R3g0d","id":"00000000005921b8","location_info":[],"neverland_ids":["00000000005921b7"],"type":1,"type__str":"DEFAULT_COMPETITOR"},"country":"Vietnam","displayname":"R3g0d","rank":6,"score_1":100,"score_2":-5414898180,"task_info":[{"penalty_attempts":0,"penalty_micros":512591800,"score":23,"score_by_test":[],"task_id":"0000000000201b7b","tests_definitely_solved":2,"tests_possibly_solved":0,"total_attempts":2},{"penalty_attempts":0,"penalty_micros":5414898180,"score":34,"score_by_test":[],"task_id":"0000000000201c01","tests_definitely_solved":2,"tests_possibly_solved":0,"total_attempts":2},{"penalty_attempts":0,"penalty_micros":3265653070,"score":43,"score_by_test":[],"task_id":"0000000000201c9a","tests_definitely_solved":2,"tests_possibly_solved":0,"total_attempts":2}]},{"competitor":{"country":["China"],"displayname":"Tian.Xie","id":"00000000004b3538","location_info":[],"neverland_ids":["00000000004b3537"],"type":1,"type__str":"DEFAULT_COMPETITOR"},"country":"China","displayname":"Tian.Xie","rank":7,"score_1":100,"score_2":-5419396860,"task_info":[{"penalty_attempts":0,"penalty_micros":770466920,"score":23,"score_by_test":[],"task_id":"0000000000201b7b","tests_definitely_solved":2,"tests_possibly_solved":0,"total_attempts":2},{"penalty_attempts":0,"penalty_micros":2249512980,"score":34,"score_by_test":[],"task_id":"0000000000201c01","tests_definitely_solved":2,"tests_possibly_solved":0,"total_attempts":2},{"penalty_attempts":0,"penalty_micros":5419396860,"score":43,"score_by_test":[],"task_id":"0000000000201c9a","tests_definitely_solved":2,"tests_possibly_solved":0,"total_attempts":2}]},{"competitor":{"country":["Singapore"],"displayname":"pwypeanut","id":"00000000004f5c34","location_info":[],"neverland_ids":["00000000004f5c33"],"type":1,"type__str":"DEFAULT_COMPETITOR"},"country":"Singapore","displayname":"pwypeanut","rank":8,"score_1":100,"score_2":-5520548170,"task_info":[{"penalty_attempts":0,"penalty_micros":241481100,"score":23,"score_by_test":[],"task_id":"0000000000201b7b","tests_definitely_solved":2,"tests_possibly_solved":0,"total_attempts":2},{"penalty_attempts":1,"penalty_micros":2874322040,"score":34,"score_by_test":[],"task_id":"0000000000201c01","tests_definitely_solved":2,"tests_possibly_solved":0,"total_attempts":3},{"penalty_attempts":0,"penalty_micros":5280548170,"score":43,"score_by_test":[],"task_id":"0000000000201c9a","tests_definitely_solved":2,"tests_possibly_solved":0,"total_attempts":2}]},{"competitor":{"country":["China"],"displayname":"mengrao","id":"0000000000576426","location_info":[],"neverland_ids":["0000000000576425"],"type":1,"type__str":"DEFAULT_COMPETITOR"},"country":"China","displayname":"mengrao","rank":9,"score_1":100,"score_2":-5979452700,"task_info":[{"penalty_attempts":0,"penalty_micros":672995460,"score":23,"score_by_test":[],"task_id":"0000000000201b7b","tests_definitely_solved":2,"tests_possibly_solved":0,"total_attempts":2},{"penalty_attempts":0,"penalty_micros":2537156180,"score":34,"score_by_test":[],"task_id":"0000000000201c01","tests_definitely_solved":2,"tests_possibly_solved":0,"total_attempts":2},{"penalty_attempts":0,"penalty_micros":5979452700,"score":43,"score_by_test":[],"task_id":"0000000000201c9a","tests_definitely_solved":2,"tests_possibly_solved":0,"total_attempts":2}]},{"competitor":{"country":["South Korea"],"displayname":"Doju","id":"00000000005cc570","location_info":[],"neverland_ids":["00000000005cc56f"],"type":1,"type__str":"DEFAULT_COMPETITOR"},"country":"South Korea","displayname":"Doju","rank":10,"score_1":100,"score_2":-6294560940,"task_info":[{"penalty_attempts":0,"penalty_micros":313581210,"score":23,"score_by_test":[],"task_id":"0000000000201b7b","tests_definitely_solved":2,"tests_possibly_solved":0,"total_attempts":2},{"penalty_attempts":1,"penalty_micros":4240300270,"score":34,"score_by_test":[],"task_id":"0000000000201c01","tests_definitely_solved":2,"tests_possibly_solved":0,"total_attempts":3},{"penalty_attempts":0,"penalty_micros":6054560940,"score":43,"score_by_test":[],"task_id":"0000000000201c9a","tests_definitely_solved":2,"tests_possibly_solved":0,"total_attempts":2}]},{"competitor":{"country":["Australia"],"displayname":"MathCrusader","id":"000000000058702a","location_info":[],"neverland_ids":["0000000000587029"],"type":1,"type__str":"DEFAULT_COMPETITOR"},"country":"Australia","displayname":"MathCrusader","rank":11,"score_1":100,"score_2":-6387024550,"task_info":[{"penalty_attempts":0,"penalty_micros":661580120,"score":23,"score_by_test":[],"task_id":"0000000000201b7b","tests_definitely_solved":2,"tests_possibly_solved":0,"total_attempts":2},{"penalty_attempts":0,"penalty_micros":6147024550,"score":34,"score_by_test":[],"task_id":"0000000000201c01","tests_definitely_solved":2,"tests_possibly_solved":0,"total_attempts":2},{"penalty_attempts":1,"penalty_micros":4095512660,"score":43,"score_by_test":[],"task_id":"0000000000201c9a","tests_definitely_solved":2,"tests_possibly_solved":0,"total_attempts":3}]},{"competitor":{"country":["Australia"],"displayname":"EvgeniSergeev","id":"0000000000625f08","location_info":[],"neverland_ids":["0000000000625f07"],"type":1,"type__str":"DEFAULT_COMPETITOR"},"country":"Australia","displayname":"EvgeniSergeev","rank":12,"score_1":100,"score_2":-6403388140,"task_info":[{"penalty_attempts":0,"penalty_micros":6403388140,"score":23,"score_by_test":[],"task_id":"0000000000201b7b","tests_definitely_solved":2,"tests_possibly_solved":0,"total_attempts":2},{"penalty_attempts":0,"penalty_micros":6344904530,"score":34,"score_by_test":[],"task_id":"0000000000201c01","tests_definitely_solved":2,"tests_possibly_solved":0,"total_attempts":2},{"penalty_attempts":0,"penalty_micros":6250978170,"score":43,"score_by_test":[],"task_id":"0000000000201c9a","tests_definitely_solved":2,"tests_possibly_solved":0,"total_attempts":2}]},{"competitor":{"country":["China"],"displayname":"ChunleiMeng","id":"00000000005d6a6c","location_info":[],"neverland_ids":["00000000005d6a6b"],"type":1,"type__str":"DEFAULT_COMPETITOR"},"country":"China","displayname":"ChunleiMeng","rank":13,"score_1":100,"score_2":-6480813210,"task_info":[{"penalty_attempts":0,"penalty_micros":674397000,"score":23,"score_by_test":[],"task_id":"0000000000201b7b","tests_definitely_solved":2,"tests_possibly_solved":0,"total_attempts":2},{"penalty_attempts":1,"penalty_micros":3362790210,"score":34,"score_by_test":[],"task_id":"0000000000201c01","tests_definitely_solved":2,"tests_possibly_solved":0,"total_attempts":3},{"penalty_attempts":0,"penalty_micros":6240813210,"score":43,"score_by_test":[],"task_id":"0000000000201c9a","tests_definitely_solved":2,"tests_possibly_solved":0,"total_attempts":2}]},{"competitor":{"country":["China"],"displayname":"Septyem","id":"00000000006399c0","location_info":[],"neverland_ids":["00000000006399bf"],"type":1,"type__str":"DEFAULT_COMPETITOR"},"country":"China","displayname":"Septyem","rank":14,"score_1":100,"score_2":-6809915080,"task_info":[{"penalty_attempts":0,"penalty_micros":659422060,"score":23,"score_by_test":[],"task_id":"0000000000201b7b","tests_definitely_solved":2,"tests_possibly_solved":0,"total_attempts":2},{"penalty_attempts":0,"penalty_micros":6809915080,"score":34,"score_by_test":[],"task_id":"0000000000201c01","tests_definitely_solved":2,"tests_possibly_solved":0,"total_attempts":2},{"penalty_attempts":0,"penalty_micros":4407658110,"score":43,"score_by_test":[],"task_id":"0000000000201c9a","tests_definitely_solved":2,"tests_possibly_solved":0,"total_attempts":2}]},{"competitor":{"country":["Thailand"],"displayname":"phirasit","id":"000000000054c1ea","location_info":[],"neverland_ids":["000000000054c1e9"],"type":1,"type__str":"DEFAULT_COMPETITOR"},"country":"Thailand","displayname":"phirasit","rank":15,"score_1":100,"score_2":-6958383140,"task_info":[{"penalty_attempts":0,"penalty_micros":956074880,"score":23,"score_by_test":[],"task_id":"0000000000201b7b","tests_definitely_solved":2,"tests_possibly_solved":0,"total_attempts":2},{"penalty_attempts":0,"penalty_micros":2375564300,"score":34,"score_by_test":[],"task_id":"0000000000201c01","tests_definitely_solved":2,"tests_possibly_solved":0,"total_attempts":2},{"penalty_attempts":1,"penalty_micros":6718383140,"score":43,"score_by_test":[],"task_id":"0000000000201c9a","tests_definitely_solved":2,"tests_possibly_solved":0,"total_attempts":3}]},{"competitor":{"country":["India"],"displayname":"gvaibhav21","id":"00000000005564ec","location_info":[],"neverland_ids":["00000000005564eb"],"type":1,"type__str":"DEFAULT_COMPETITOR"},"country":"India","displayname":"gvaibhav21","rank":16,"score_1":100,"score_2":-7181428550,"task_info":[{"penalty_attempts":0,"penalty_micros":783212580,"score":23,"score_by_test":[],"task_id":"0000000000201b7b","tests_definitely_solved":2,"tests_possibly_solved":0,"total_attempts":2},{"penalty_attempts":0,"penalty_micros":7181428550,"score":34,"score_by_test":[],"task_id":"0000000000201c01","tests_definitely_solved":2,"tests_possibly_solved":0,"total_attempts":2},{"penalty_attempts":0,"penalty_micros":4554076920,"score":43,"score_by_test":[],"task_id":"0000000000201c9a","tests_definitely_solved":2,"tests_possibly_solved":0,"total_attempts":2}]},{"competitor":{"country":["China"],"displayname":"imoeso","id":"00000000004bccf0","location_info":[],"neverland_ids":["00000000004bccef"],"type":1,"type__str":"DEFAULT_COMPETITOR"},"country":"China","displayname":"imoeso","rank":17,"score_1":100,"score_2":-7192126050,"task_info":[{"penalty_attempts":0,"penalty_micros":1066894480,"score":23,"score_by_test":[],"task_id":"0000000000201b7b","tests_definitely_solved":2,"tests_possibly_solved":0,"total_attempts":2},{"penalty_attempts":0,"penalty_micros":4928553850,"score":34,"score_by_test":[],"task_id":"0000000000201c01","tests_definitely_solved":2,"tests_possibly_solved":0,"total_attempts":2},{"penalty_attempts":0,"penalty_micros":7192126050,"score":43,"score_by_test":[],"task_id":"0000000000201c9a","tests_definitely_solved":2,"tests_possibly_solved":0,"total_attempts":2}]},{"competitor":{"country":["China"],"displayname":"anorange0409","id":"000000000061bd26","location_info":[],"neverland_ids":["000000000061bd25"],"type":1,"type__str":"DEFAULT_COMPETITOR"},"country":"China","displayname":"anorange0409","rank":18,"score_1":100,"score_2":-7607850850,"task_info":[{"penalty_attempts":0,"penalty_micros":675694340,"score":23,"score_by_test":[],"task_id":"0000000000201b7b","tests_definitely_solved":2,"tests_possibly_solved":0,"total_attempts":2},{"penalty_attempts":0,"penalty_micros":7607850850,"score":34,"score_by_test":[],"task_id":"0000000000201c01","tests_definitely_solved":2,"tests_possibly_solved":0,"total_attempts":2},{"penalty_attempts":0,"penalty_micros":3851205930,"score":43,"score_by_test":[],"task_id":"0000000000201c9a","tests_definitely_solved":2,"tests_possibly_solved":0,"total_attempts":2}]},{"competitor":{"country":["Thailand"],"displayname":"thanabhat","id":"000000000048a454","location_info":[],"neverland_ids":["000000000048a453"],"type":1,"type__str":"DEFAULT_COMPETITOR"},"country":"Thailand","displayname":"thanabhat","rank":19,"score_1":100,"score_2":-8541288310,"task_info":[{"penalty_attempts":0,"penalty_micros":1324470570,"score":23,"score_by_test":[],"task_id":"0000000000201b7b","tests_definitely_solved":2,"tests_possibly_solved":0,"total_attempts":2},{"penalty_attempts":0,"penalty_micros":4660352700,"score":34,"score_by_test":[],"task_id":"0000000000201c01","tests_definitely_solved":2,"tests_possibly_solved":0,"total_attempts":2},{"penalty_attempts":1,"penalty_micros":8301288310,"score":43,"score_by_test":[],"task_id":"0000000000201c9a","tests_definitely_solved":2,"tests_possibly_solved":0,"total_attempts":3}]},{"competitor":{"country":["China"],"displayname":"pkwv","id":"00000000004c626c","location_info":[],"neverland_ids":["00000000004c626b"],"type":1,"type__str":"DEFAULT_COMPETITOR"},"country":"China","displayname":"pkwv","rank":20,"score_1":100,"score_2":-8732937560,"task_info":[{"penalty_attempts":0,"penalty_micros":986231370,"score":23,"score_by_test":[],"task_id":"0000000000201b7b","tests_definitely_solved":2,"tests_possibly_solved":0,"total_attempts":2},{"penalty_attempts":0,"penalty_micros":8732937560,"score":34,"score_by_test":[],"task_id":"0000000000201c01","tests_definitely_solved":2,"tests_possibly_solved":0,"total_attempts":2},{"penalty_attempts":0,"penalty_micros":4054866230,"score":43,"score_by_test":[],"task_id":"0000000000201c9a","tests_definitely_solved":2,"tests_possibly_solved":0,"total_attempts":2}]},{"competitor":{"country":["China"],"displayname":"chlxyd","id":"00000000006114c4","location_info":[],"neverland_ids":["00000000006114c3"],"type":1,"type__str":"DEFAULT_COMPETITOR"},"country":"China","displayname":"chlxyd","rank":21,"score_1":100,"score_2":-8848014850,"task_info":[{"penalty_attempts":0,"penalty_micros":3633138420,"score":23,"score_by_test":[],"task_id":"0000000000201b7b","tests_definitely_solved":2,"tests_possibly_solved":0,"total_attempts":2},{"penalty_attempts":0,"penalty_micros":2956892810,"score":34,"score_by_test":[],"task_id":"0000000000201c01","tests_definitely_solved":2,"tests_possibly_solved":0,"total_attempts":2},{"penalty_attempts":0,"penalty_micros":8848014850,"score":43,"score_by_test":[],"task_id":"0000000000201c9a","tests_definitely_solved":2,"tests_possibly_solved":0,"total_attempts":2}]},{"competitor":{"country":["China"],"displayname":"whatyouthink","id":"00000000005dfb96","location_info":[],"neverland_ids":["00000000005dfb95"],"type":1,"type__str":"DEFAULT_COMPETITOR"},"country":"China","displayname":"whatyouthink","rank":22,"score_1":100,"score_2":-8999233770,"task_info":[{"penalty_attempts":0,"penalty_micros":1151618470,"score":23,"score_by_test":[],"task_id":"0000000000201b7b","tests_definitely_solved":2,"tests_possibly_solved":0,"total_attempts":2},{"penalty_attempts":1,"penalty_micros":8759233770,"score":34,"score_by_test":[],"task_id":"0000000000201c01","tests_definitely_solved":2,"tests_possibly_solved":0,"total_attempts":3},{"penalty_attempts":0,"penalty_micros":8153696010,"score":43,"score_by_test":[],"task_id":"0000000000201c9a","tests_definitely_solved":2,"tests_possibly_solved":0,"total_attempts":2}]},{"competitor":{"country":["Bangladesh"],"displayname":"fsshakkhor","id":"00000000004adfe6","location_info":[],"neverland_ids":["00000000004adfe5"],"type":1,"type__str":"DEFAULT_COMPETITOR"},"country":"Bangladesh","displayname":"fsshakkhor","rank":23,"score_1":100,"score_2":-9082097220,"task_info":[{"penalty_attempts":0,"penalty_micros":2325337060,"score":23,"score_by_test":[],"task_id":"0000000000201b7b","tests_definitely_solved":2,"tests_possibly_solved":0,"total_attempts":2},{"penalty_attempts":0,"penalty_micros":9082097220,"score":34,"score_by_test":[],"task_id":"0000000000201c01","tests_definitely_solved":2,"tests_possibly_solved":0,"total_attempts":2},{"penalty_attempts":0,"penalty_micros":5733451960,"score":43,"score_by_test":[],"task_id":"0000000000201c9a","tests_definitely_solved":2,"tests_possibly_solved":0,"total_attempts":2}]},{"competitor":{"country":["China"],"displayname":"Frank1992","id":"00000000004ba84e","location_info":[],"neverland_ids":["00000000004ba84d"],"type":1,"type__str":"DEFAULT_COMPETITOR"},"country":"China","displayname":"Frank1992","rank":24,"score_1":100,"score_2":-9470068700,"task_info":[{"penalty_attempts":0,"penalty_micros":681357770,"score":23,"score_by_test":[],"task_id":"0000000000201b7b","tests_definitely_solved":2,"tests_possibly_solved":0,"total_attempts":2},{"penalty_attempts":0,"penalty_micros":8990068700,"score":34,"score_by_test":[],"task_id":"0000000000201c01","tests_definitely_solved":2,"tests_possibly_solved":0,"total_attempts":2},{"penalty_attempts":2,"penalty_micros":5331465410,"score":43,"score_by_test":[],"task_id":"0000000000201c9a","tests_definitely_solved":2,"tests_possibly_solved":0,"total_attempts":4}]},{"competitor":{"country":[],"displayname":"Excited violet turtle","id":"000000000045fe18","location_info":[],"neverland_ids":["000000000045fe17"],"type":1,"type__str":"DEFAULT_COMPETITOR"},"country":"","displayname":"Excited violet turtle","rank":25,"score_1":100,"score_2":-10744294070,"task_info":[{"penalty_attempts":0,"penalty_micros":1019203480,"score":23,"score_by_test":[],"task_id":"0000000000201b7b","tests_definitely_solved":2,"tests_possibly_solved":0,"total_attempts":2},{"penalty_attempts":0,"penalty_micros":7046940430,"score":34,"score_by_test":[],"task_id":"0000000000201c01","tests_definitely_solved":2,"tests_possibly_solved":0,"total_attempts":2},{"penalty_attempts":0,"penalty_micros":10744294070,"score":43,"score_by_test":[],"task_id":"0000000000201c9a","tests_definitely_solved":2,"tests_possibly_solved":0,"total_attempts":2}]},{"competitor":{"country":["Vietnam"],"displayname":"tanphatls987","id":"000000000051885a","location_info":[],"neverland_ids":["0000000000518859"],"type":1,"type__str":"DEFAULT_COMPETITOR"},"country":"Vietnam","displayname":"tanphatls987","rank":26,"score_1":100,"score_2":-10797000160,"task_info":[{"penalty_attempts":0,"penalty_micros":973941670,"score":23,"score_by_test":[],"task_id":"0000000000201b7b","tests_definitely_solved":2,"tests_possibly_solved":0,"total_attempts":2},{"penalty_attempts":0,"penalty_micros":10077000160,"score":34,"score_by_test":[],"task_id":"0000000000201c01","tests_definitely_solved":2,"tests_possibly_solved":0,"total_attempts":2},{"penalty_attempts":3,"penalty_micros":5210307440,"score":43,"score_by_test":[],"task_id":"0000000000201c9a","tests_definitely_solved":2,"tests_possibly_solved":0,"total_attempts":5}]},{"competitor":{"country":["Ukraine"],"displayname":"andrewsk","id":"00000000005f518c","location_info":[],"neverland_ids":["00000000005f518b"],"type":1,"type__str":"DEFAULT_COMPETITOR"},"country":"Ukraine","displayname":"andrewsk","rank":27,"score_1":84,"score_2":-10938844130,"task_info":[{"penalty_attempts":0,"penalty_micros":1567416890,"score":7,"score_by_test":[],"task_id":"0000000000201b7b","tests_definitely_solved":1,"tests_possibly_solved":0,"total_attempts":2},{"penalty_attempts":1,"penalty_micros":10698844130,"score":34,"score_by_test":[],"task_id":"0000000000201c01","tests_definitely_solved":2,"tests_possibly_solved":0,"total_attempts":3},{"penalty_attempts":0,"penalty_micros":9275647090,"score":43,"score_by_test":[],"task_id":"0000000000201c9a","tests_definitely_solved":2,"tests_possibly_solved":0,"total_attempts":2}]},{"competitor":{"country":["China"],"displayname":"yubowenok","id":"0000000000590b52","location_info":[],"neverland_ids":["0000000000590b51"],"type":1,"type__str":"DEFAULT_COMPETITOR"},"country":"China","displayname":"yubowenok","rank":28,"score_1":79,"score_2":-6956317520,"task_info":[{"penalty_attempts":0,"penalty_micros":1043642760,"score":23,"score_by_test":[],"task_id":"0000000000201b7b","tests_definitely_solved":2,"tests_possibly_solved":0,"total_attempts":2},{"penalty_attempts":0,"penalty_micros":2409420670,"score":13,"score_by_test":[],"task_id":"0000000000201c01","tests_definitely_solved":1,"tests_possibly_solved":0,"total_attempts":2},{"penalty_attempts":0,"penalty_micros":6956317520,"score":43,"score_by_test":[],"task_id":"0000000000201c9a","tests_definitely_solved":2,"tests_possibly_solved":0,"total_attempts":2}]},{"competitor":{"country":["China"],"displayname":"supasaya","id":"000000000053aa14","location_info":[],"neverland_ids":["000000000053aa13"],"type":1,"type__str":"DEFAULT_COMPETITOR"},"country":"China","displayname":"supasaya","rank":29,"score_1":79,"score_2":-8001545100,"task_info":[{"penalty_attempts":0,"penalty_micros":403559270,"score":23,"score_by_test":[],"task_id":"0000000000201b7b","tests_definitely_solved":2,"tests_possibly_solved":0,"total_attempts":2},{"penalty_attempts":0,"penalty_micros":2714449840,"score":13,"score_by_test":[],"task_id":"0000000000201c01","tests_definitely_solved":1,"tests_possibly_solved":0,"total_attempts":2},{"penalty_attempts":0,"penalty_micros":8001545100,"score":43,"score_by_test":[],"task_id":"0000000000201c9a","tests_definitely_solved":2,"tests_possibly_solved":0,"total_attempts":2}]},{"competitor":{"country":["China"],"displayname":"fivekai","id":"000000000059dbf6","location_info":[],"neverland_ids":["000000000059dbf5"],"type":1,"type__str":"DEFAULT_COMPETITOR"},"country":"China","displayname":"fivekai","rank":30,"score_1":79,"score_2":-8440040370,"task_info":[{"penalty_attempts":0,"penalty_micros":1740724170,"score":23,"score_by_test":[],"task_id":"0000000000201b7b","tests_definitely_solved":2,"tests_possibly_solved":0,"total_attempts":2},{"penalty_attempts":0,"penalty_micros":4872798480,"score":13,"score_by_test":[],"task_id":"0000000000201c01","tests_definitely_solved":1,"tests_possibly_solved":0,"total_attempts":1},{"penalty_attempts":0,"penalty_micros":8440040370,"score":43,"score_by_test":[],"task_id":"0000000000201c9a","tests_definitely_solved":2,"tests_possibly_solved":0,"total_attempts":2}]},{"competitor":{"country":["Vietnam"],"displayname":"daip","id":"0000000000541e2c","location_info":[],"neverland_ids":["0000000000541e2b"],"type":1,"type__str":"DEFAULT_COMPETITOR"},"country":"Vietnam","displayname":"daip","rank":31,"score_1":79,"score_2":-8694256580,"task_info":[{"penalty_attempts":0,"penalty_micros":480644150,"score":23,"score_by_test":[],"task_id":"0000000000201b7b","tests_definitely_solved":2,"tests_possibly_solved":0,"total_attempts":2},{"penalty_attempts":2,"penalty_micros":7734256580,"score":13,"score_by_test":[],"task_id":"0000000000201c01","tests_definitely_solved":1,"tests_possibly_solved":0,"total_attempts":4},{"penalty_attempts":2,"penalty_micros":4803948490,"score":43,"score_by_test":[],"task_id":"0000000000201c9a","tests_definitely_solved":2,"tests_possibly_solved":0,"total_attempts":4}]},{"competitor":{"country":["New Zealand"],"displayname":"voxel","id":"0000000000576202","location_info":[],"neverland_ids":["0000000000576201"],"type":1,"type__str":"DEFAULT_COMPETITOR"},"country":"New Zealand","displayname":"voxel","rank":32,"score_1":79,"score_2":-8924044950,"task_info":[{"penalty_attempts":0,"penalty_micros":1956394700,"score":23,"score_by_test":[],"task_id":"0000000000201b7b","tests_definitely_solved":2,"tests_possibly_solved":0,"total_attempts":2},{"penalty_attempts":0,"penalty_micros":5514559490,"score":13,"score_by_test":[],"task_id":"0000000000201c01","tests_definitely_solved":1,"tests_possibly_solved":0,"total_attempts":2},{"penalty_attempts":0,"penalty_micros":8924044950,"score":43,"score_by_test":[],"task_id":"0000000000201c9a","tests_definitely_solved":2,"tests_possibly_solved":0,"total_attempts":2}]},{"competitor":{"country":["India"],"displayname":"sharadkejriwal","id":"00000000005efa74","location_info":[],"neverland_ids":["00000000005efa73"],"type":1,"type__str":"DEFAULT_COMPETITOR"},"country":"India","displayname":"sharadkejriwal","rank":33,"score_1":79,"score_2":-9736572610,"task_info":[{"penalty_attempts":0,"penalty_micros":826715950,"score":23,"score_by_test":[],"task_id":"0000000000201b7b","tests_definitely_solved":2,"tests_possibly_solved":0,"total_attempts":2},{"penalty_attempts":1,"penalty_micros":9016572610,"score":13,"score_by_test":[],"task_id":"0000000000201c01","tests_definitely_solved":1,"tests_possibly_solved":0,"total_attempts":2},{"penalty_attempts":2,"penalty_micros":7424051610,"score":43,"score_by_test":[],"task_id":"0000000000201c9a","tests_definitely_solved":2,"tests_possibly_solved":0,"total_attempts":4}]},{"competitor":{"country":["China"],"displayname":"css","id":"000000000061f986","location_info":[],"neverland_ids":["000000000061f985"],"type":1,"type__str":"DEFAULT_COMPETITOR"},"country":"China","displayname":"css","rank":34,"score_1":79,"score_2":-10392959460,"task_info":[{"penalty_attempts":0,"penalty_micros":1215951660,"score":23,"score_by_test":[],"task_id":"0000000000201b7b","tests_definitely_solved":2,"tests_possibly_solved":0,"total_attempts":2},{"penalty_attempts":0,"penalty_micros":4786900880,"score":13,"score_by_test":[],"task_id":"0000000000201c01","tests_definitely_solved":1,"tests_possibly_solved":0,"total_attempts":2},{"penalty_attempts":1,"penalty_micros":10152959460,"score":43,"score_by_test":[],"task_id":"0000000000201c9a","tests_definitely_solved":2,"tests_possibly_solved":0,"total_attempts":3}]},{"competitor":{"country":["Uzbekistan"],"displayname":"shavkatkhusanov","id":"000000000047da76","location_info":[],"neverland_ids":["000000000047da75"],"type":1,"type__str":"DEFAULT_COMPETITOR"},"country":"Uzbekistan","displayname":"shavkatkhusanov","rank":35,"score_1":79,"score_2":-10456666190,"task_info":[{"penalty_attempts":0,"penalty_micros":1117152950,"score":23,"score_by_test":[],"task_id":"0000000000201b7b","tests_definitely_solved":2,"tests_possibly_solved":0,"total_attempts":2},{"penalty_attempts":1,"penalty_micros":6473686900,"score":13,"score_by_test":[],"task_id":"0000000000201c01","tests_definitely_solved":1,"tests_possibly_solved":0,"total_attempts":3},{"penalty_attempts":0,"penalty_micros":10216666190,"score":43,"score_by_test":[],"task_id":"0000000000201c9a","tests_definitely_solved":2,"tests_possibly_solved":0,"total_attempts":2}]},{"competitor":{"country":["India"],"displayname":"optimist","id":"00000000004ff340","location_info":[],"neverland_ids":["00000000004ff33f"],"type":1,"type__str":"DEFAULT_COMPETITOR"},"country":"India","displayname":"optimist","rank":36,"score_1":79,"score_2":-10537309540,"task_info":[{"penalty_attempts":0,"penalty_micros":1026689120,"score":23,"score_by_test":[],"task_id":"0000000000201b7b","tests_definitely_solved":2,"tests_possibly_solved":0,"total_attempts":2},{"penalty_attempts":0,"penalty_micros":4371801640,"score":13,"score_by_test":[],"task_id":"0000000000201c01","tests_definitely_solved":1,"tests_possibly_solved":0,"total_attempts":2},{"penalty_attempts":0,"penalty_micros":10537309540,"score":43,"score_by_test":[],"task_id":"0000000000201c9a","tests_definitely_solved":2,"tests_possibly_solved":0,"total_attempts":2}]},{"competitor":{"country":["Taiwan"],"displayname":"hank55663","id":"0000000000490950","location_info":[],"neverland_ids":["000000000049094f"],"type":1,"type__str":"DEFAULT_COMPETITOR"},"country":"Taiwan","displayname":"hank55663","rank":37,"score_1":68,"score_2":-2488779120,"task_info":[{"penalty_attempts":0,"penalty_micros":501497480,"score":23,"score_by_test":[],"task_id":"0000000000201b7b","tests_definitely_solved":2,"tests_possibly_solved":0,"total_attempts":2},{"penalty_attempts":0,"penalty_micros":1640706720,"score":34,"score_by_test":[],"task_id":"0000000000201c01","tests_definitely_solved":2,"tests_possibly_solved":0,"total_attempts":2},{"penalty_attempts":0,"penalty_micros":2488779120,"score":11,"score_by_test":[],"task_id":"0000000000201c9a","tests_definitely_solved":1,"tests_possibly_solved":0,"total_attempts":2}]},{"competitor":{"country":["South Korea"],"displayname":"kazel","id":"00000000004b2c8c","location_info":[],"neverland_ids":["00000000004b2c8b"],"type":1,"type__str":"DEFAULT_COMPETITOR"},"country":"South Korea","displayname":"kazel","rank":38,"score_1":68,"score_2":-2615076420,"task_info":[{"penalty_attempts":0,"penalty_micros":557643480,"score":23,"score_by_test":[],"task_id":"0000000000201b7b","tests_definitely_solved":2,"tests_possibly_solved":0,"total_attempts":2},{"penalty_attempts":0,"penalty_micros":1673754460,"score":34,"score_by_test":[],"task_id":"0000000000201c01","tests_definitely_solved":2,"tests_possibly_solved":0,"total_attempts":2},{"penalty_attempts":1,"penalty_micros":2375076420,"score":11,"score_by_test":[],"task_id":"0000000000201c9a","tests_definitely_solved":1,"tests_possibly_solved":0,"total_attempts":3}]},{"competitor":{"country":["Hong Kong"],"displayname":"Artie","id":"000000000051a14a","location_info":[],"neverland_ids":["000000000051a149"],"type":1,"type__str":"DEFAULT_COMPETITOR"},"country":"Hong Kong","displayname":"Artie","rank":39,"score_1":68,"score_2":-3306142610,"task_info":[{"penalty_attempts":0,"penalty_micros":699734120,"score":23,"score_by_test":[],"task_id":"0000000000201b7b","tests_definitely_solved":2,"tests_possibly_solved":0,"total_attempts":2},{"penalty_attempts":0,"penalty_micros":2399977510,"score":34,"score_by_test":[],"task_id":"0000000000201c01","tests_definitely_solved":2,"tests_possibly_solved":0,"total_attempts":2},{"penalty_attempts":0,"penalty_micros":3306142610,"score":11,"score_by_test":[],"task_id":"0000000000201c9a","tests_definitely_solved":1,"tests_possibly_solved":0,"total_attempts":2}]},{"competitor":{"country":["Vietnam"],"displayname":"abcdef6199","id":"00000000005b49b4","location_info":[],"neverland_ids":["00000000005b49b3"],"type":1,"type__str":"DEFAULT_COMPETITOR"},"country":"Vietnam","displayname":"abcdef6199","rank":40,"score_1":68,"score_2":-3493448670,"task_info":[{"penalty_attempts":0,"penalty_micros":2035166030,"score":23,"score_by_test":[],"task_id":"0000000000201b7b","tests_definitely_solved":2,"tests_possibly_solved":0,"total_attempts":2},{"penalty_attempts":0,"penalty_micros":2869908390,"score":34,"score_by_test":[],"task_id":"0000000000201c01","tests_definitely_solved":2,"tests_possibly_solved":0,"total_attempts":2},{"penalty_attempts":0,"penalty_micros":3493448670,"score":11,"score_by_test":[],"task_id":"0000000000201c9a","tests_definitely_solved":1,"tests_possibly_solved":0,"total_attempts":2}]},{"competitor":{"country":["China"],"displayname":"xyz2019","id":"00000000005025fe","location_info":[],"neverland_ids":["00000000005025fd"],"type":1,"type__str":"DEFAULT_COMPETITOR"},"country":"China","displayname":"xyz2019","rank":41,"score_1":68,"score_2":-3646597240,"task_info":[{"penalty_attempts":0,"penalty_micros":537017820,"score":23,"score_by_test":[],"task_id":"0000000000201b7b","tests_definitely_solved":2,"tests_possibly_solved":0,"total_attempts":2},{"penalty_attempts":0,"penalty_micros":3646597240,"score":34,"score_by_test":[],"task_id":"0000000000201c01","tests_definitely_solved":2,"tests_possibly_solved":0,"total_attempts":2},{"penalty_attempts":0,"penalty_micros":2110726880,"score":11,"score_by_test":[],"task_id":"0000000000201c9a","tests_definitely_solved":1,"tests_possibly_solved":0,"total_attempts":1}]},{"competitor":{"country":["China"],"displayname":"rsola","id":"000000000050e608","location_info":[],"neverland_ids":["000000000050e607"],"type":1,"type__str":"DEFAULT_COMPETITOR"},"country":"China","displayname":"rsola","rank":42,"score_1":68,"score_2":-3814438230,"task_info":[{"penalty_attempts":0,"penalty_micros":500994060,"score":23,"score_by_test":[],"task_id":"0000000000201b7b","tests_definitely_solved":2,"tests_possibly_solved":0,"total_attempts":2},{"penalty_attempts":0,"penalty_micros":1506264500,"score":34,"score_by_test":[],"task_id":"0000000000201c01","tests_definitely_solved":2,"tests_possibly_solved":0,"total_attempts":2},{"penalty_attempts":0,"penalty_micros":3814438230,"score":11,"score_by_test":[],"task_id":"0000000000201c9a","tests_definitely_solved":1,"tests_possibly_solved":0,"total_attempts":2}]},{"competitor":{"country":["China"],"displayname":"shdut","id":"0000000000515efa","location_info":[],"neverland_ids":["0000000000515ef9"],"type":1,"type__str":"DEFAULT_COMPETITOR"},"country":"China","displayname":"shdut","rank":43,"score_1":68,"score_2":-4029853510,"task_info":[{"penalty_attempts":0,"penalty_micros":972669710,"score":23,"score_by_test":[],"task_id":"0000000000201b7b","tests_definitely_solved":2,"tests_possibly_solved":0,"total_attempts":2},{"penalty_attempts":0,"penalty_micros":3363714900,"score":34,"score_by_test":[],"task_id":"0000000000201c01","tests_definitely_solved":2,"tests_possibly_solved":0,"total_attempts":2},{"penalty_attempts":0,"penalty_micros":4029853510,"score":11,"score_by_test":[],"task_id":"0000000000201c9a","tests_definitely_solved":1,"tests_possibly_solved":0,"total_attempts":2}]},{"competitor":{"country":["Vietnam"],"displayname":"ladpro98","id":"00000000005c516a","location_info":[],"neverland_ids":["00000000005c5169"],"type":1,"type__str":"DEFAULT_COMPETITOR"},"country":"Vietnam","displayname":"ladpro98","rank":44,"score_1":68,"score_2":-4099261390,"task_info":[{"penalty_attempts":0,"penalty_micros":554007010,"score":23,"score_by_test":[],"task_id":"0000000000201b7b","tests_definitely_solved":2,"tests_possibly_solved":0,"total_attempts":2},{"penalty_attempts":0,"penalty_micros":2219992390,"score":34,"score_by_test":[],"task_id":"0000000000201c01","tests_definitely_solved":2,"tests_possibly_solved":0,"total_attempts":2},{"penalty_attempts":0,"penalty_micros":4099261390,"score":11,"score_by_test":[],"task_id":"0000000000201c9a","tests_definitely_solved":1,"tests_possibly_solved":0,"total_attempts":2}]},{"competitor":{"country":["Indonesia"],"displayname":"aarcturus","id":"00000000004bf6de","location_info":[],"neverland_ids":["00000000004bf6dd"],"type":1,"type__str":"DEFAULT_COMPETITOR"},"country":"Indonesia","displayname":"aarcturus","rank":45,"score_1":68,"score_2":-4168965460,"task_info":[{"penalty_attempts":0,"penalty_micros":1046549840,"score":23,"score_by_test":[],"task_id":"0000000000201b7b","tests_definitely_solved":2,"tests_possibly_solved":0,"total_attempts":2},{"penalty_attempts":0,"penalty_micros":4168965460,"score":34,"score_by_test":[],"task_id":"0000000000201c01","tests_definitely_solved":2,"tests_possibly_solved":0,"total_attempts":2},{"penalty_attempts":0,"penalty_micros":1975067240,"score":11,"score_by_test":[],"task_id":"0000000000201c9a","tests_definitely_solved":1,"tests_possibly_solved":0,"total_attempts":2}]},{"competitor":{"country":["Brazil"],"displayname":"ivanilos","id":"000000000047f56a","location_info":[],"neverland_ids":["000000000047f569"],"type":1,"type__str":"DEFAULT_COMPETITOR"},"country":"Brazil","displayname":"ivanilos","rank":46,"score_1":68,"score_2":-4186776290,"task_info":[{"penalty_attempts":0,"penalty_micros":1067705870,"score":23,"score_by_test":[],"task_id":"0000000000201b7b","tests_definitely_solved":2,"tests_possibly_solved":0,"total_attempts":2},{"penalty_attempts":0,"penalty_micros":3765376560,"score":34,"score_by_test":[],"task_id":"0000000000201c01","tests_definitely_solved":2,"tests_possibly_solved":0,"total_attempts":2},{"penalty_attempts":0,"penalty_micros":4186776290,"score":11,"score_by_test":[],"task_id":"0000000000201c9a","tests_definitely_solved":1,"tests_possibly_solved":0,"total_attempts":1}]},{"competitor":{"country":["China"],"displayname":"zkGaia","id":"00000000004d8ab0","location_info":[],"neverland_ids":["00000000004d8aaf"],"type":1,"type__str":"DEFAULT_COMPETITOR"},"country":"China","displayname":"zkGaia","rank":47,"score_1":68,"score_2":-4397509970,"task_info":[{"penalty_attempts":0,"penalty_micros":514623740,"score":23,"score_by_test":[],"task_id":"0000000000201b7b","tests_definitely_solved":2,"tests_possibly_solved":0,"total_attempts":2},{"penalty_attempts":0,"penalty_micros":2435502320,"score":34,"score_by_test":[],"task_id":"0000000000201c01","tests_definitely_solved":2,"tests_possibly_solved":0,"total_attempts":2},{"penalty_attempts":0,"penalty_micros":4397509970,"score":11,"score_by_test":[],"task_id":"0000000000201c9a","tests_definitely_solved":1,"tests_possibly_solved":0,"total_attempts":2}]},{"competitor":{"country":["China"],"displayname":"wyl8899","id":"00000000004d3190","location_info":[],"neverland_ids":["00000000004d318f"],"type":1,"type__str":"DEFAULT_COMPETITOR"},"country":"China","displayname":"wyl8899","rank":48,"score_1":68,"score_2":-4410629680,"task_info":[{"penalty_attempts":0,"penalty_micros":781015190,"score":23,"score_by_test":[],"task_id":"0000000000201b7b","tests_definitely_solved":2,"tests_possibly_solved":0,"total_attempts":2},{"penalty_attempts":0,"penalty_micros":1820081570,"score":34,"score_by_test":[],"task_id":"0000000000201c01","tests_definitely_solved":2,"tests_possibly_solved":0,"total_attempts":2},{"penalty_attempts":1,"penalty_micros":4170629680,"score":11,"score_by_test":[],"task_id":"0000000000201c9a","tests_definitely_solved":1,"tests_possibly_solved":0,"total_attempts":3}]},{"competitor":{"country":["China"],"displayname":"caojunjie","id":"00000000004d74de","location_info":[],"neverland_ids":["00000000004d74dd"],"type":1,"type__str":"DEFAULT_COMPETITOR"},"country":"China","displayname":"caojunjie","rank":49,"score_1":68,"score_2":-4737074630,"task_info":[{"penalty_attempts":0,"penalty_micros":1225973990,"score":23,"score_by_test":[],"task_id":"0000000000201b7b","tests_definitely_solved":2,"tests_possibly_solved":0,"total_attempts":2},{"penalty_attempts":0,"penalty_micros":4737074630,"score":34,"score_by_test":[],"task_id":"0000000000201c01","tests_definitely_solved":2,"tests_possibly_solved":0,"total_attempts":2},{"penalty_attempts":0,"penalty_micros":3168401740,"score":11,"score_by_test":[],"task_id":"0000000000201c9a","tests_definitely_solved":1,"tests_possibly_solved":0,"total_attempts":2}]},{"competitor":{"country":["China"],"displayname":"zlper","id":"0000000000613abe","location_info":[],"neverland_ids":["0000000000613abd"],"type":1,"type__str":"DEFAULT_COMPETITOR"},"country":"China","displayname":"zlper","rank":50,"score_1":68,"score_2":-5259364960,"task_info":[{"penalty_attempts":0,"penalty_micros":651226930,"score":23,"score_by_test":[],"task_id":"0000000000201b7b","tests_definitely_solved":2,"tests_possibly_solved":0,"total_attempts":2},{"penalty_attempts":1,"penalty_micros":5019364960,"score":34,"score_by_test":[],"task_id":"0000000000201c01","tests_definitely_solved":2,"tests_possibly_solved":0,"total_attempts":3},{"penalty_attempts":0,"penalty_micros":1584759370,"score":11,"score_by_test":[],"task_id":"0000000000201c9a","tests_definitely_solved":1,"tests_possibly_solved":0,"total_attempts":1}]}]}
